fasthugs/__init__.py
fasthugs/_nbdev.py
fasthugs/data.py
fasthugs/learner.py
fasthugs/metrics.py
fasthugs-0.0.1.dist-info/LICENSE
fasthugs-0.0.1.dist-info/METADATA
fasthugs-0.0.1.dist-info/WHEEL
fasthugs-0.0.1.dist-info/entry_points.txt
fasthugs-0.0.1.dist-info/top_level.txt
fasthugs-0.0.1.dist-info/RECORD
