Metadata-Version: 2.1
Name: fasthugs
Version: 0.0.1
Summary: A description of your project
Home-page: https://github.com/aikindergarten/fasthugs/tree/master/
Author: aikindergarten
Author-email: aruthart@gmail.com
License: Apache Software License 2.0
Keywords: transformers,fastai
Platform: UNKNOWN
Classifier: Development Status :: 3 - Alpha
Classifier: Intended Audience :: Developers
Classifier: Natural Language :: English
Classifier: Programming Language :: Python :: 3.6
Classifier: Programming Language :: Python :: 3.7
Classifier: Programming Language :: Python :: 3.8
Classifier: License :: OSI Approved :: Apache Software License
Requires-Python: >=3.6
Requires-Dist: pip
Requires-Dist: packaging
Requires-Dist: torch (>=1.7.1)
Requires-Dist: fastai (>=2.2.2)
Requires-Dist: fastcore
Requires-Dist: transformers
Requires-Dist: datasets
Provides-Extra: dev
